fuckllm/__init__.py
fuckllm/py.typed
fuckllm/agent/__init__.py
fuckllm/agent/_react.py
fuckllm/config/__init__.py
fuckllm/config/_model.py
fuckllm/config/_print.py
fuckllm/format/__init__.py
fuckllm/format/_mcp.py
fuckllm/format/_print.py
fuckllm/memory/__init__.py
fuckllm/memory/_instant_memory.py
fuckllm/model/__init__.py
fuckllm/model/_call_llm.py
fuckllm/tools/__init__.py
fuckllm/tools/_mcp.py
fuckllm/tools/_register.py
fuckllm/tts/__init__.py
fuckllm/tts/_ali.py
fuckllm/tts/_qwen.py
fuckllm/tts/_tts.py
fuckllm/tts/_tts_cache.py
fuckllm/tts/_tts_realtime.py
fuckllm/tts/_tts_synthesis.py
fuckllm/tts/x.py
fuckllm/tts/xx.py
fuckllm/type/__init__.py
fuckllm/type/_type.py
fuckllm/utils/__init__.py
fuckllm/utils/_b64_pcm_player.py
fuckllm/utils/_base_tools.py
fuckllm/utils/_file_cache.py
fuckllm/utils/_parser_mcp.py
fuckllm/utils/_tts_cache.py
fuckllm/vb/__init__.py
fuckllm/vb/_vb_chroma.py
fuckllm/vb/_vb_json.py
fuckllm-0.1.0.dist-info/METADATA
fuckllm-0.1.0.dist-info/WHEEL
fuckllm-0.1.0.dist-info/top_level.txt
fuckllm-0.1.0.dist-info/RECORD
