Metadata-Version: 2.4
Name: fuckllm
Version: 0.1.0
Summary: A comprehensive AI agent framework with memory, tools, and TTS capabilities
Author-email: xiasang <aixiasang@163.com>
License-Expression: MIT
Project-URL: Homepage, https://github.com/aixiasang/fuckllm
Project-URL: Repository, https://github.com/aixiasang/fuckllm
Project-URL: Documentation, https://github.com/aixiasang/fuckllm/blob/main/README.md
Keywords: ai,agent,memory,tts,llm
Classifier: Development Status :: 3 - Alpha
Classifier: Intended Audience :: Developers
Classifier: Programming Language :: Python :: 3
Classifier: Programming Language :: Python :: 3.10
Classifier: Programming Language :: Python :: 3.11
Classifier: Programming Language :: Python :: 3.12
Requires-Python: >=3.10
Requires-Dist: openai>=1.0.0
Requires-Dist: numpy>=1.24.0
Requires-Dist: websockets>=11.0
Requires-Dist: mcp>=0.9.0
Provides-Extra: tts
Requires-Dist: dashscope>=1.14.0; extra == "tts"
Requires-Dist: pyaudio>=0.2.13; extra == "tts"
Provides-Extra: vectordb
Requires-Dist: chromadb>=0.4.0; extra == "vectordb"
Provides-Extra: full
Requires-Dist: fuckllm[tts,vectordb]; extra == "full"
Provides-Extra: dev
Requires-Dist: pytest>=7.0.0; extra == "dev"
Requires-Dist: pytest-asyncio>=0.21.0; extra == "dev"
Requires-Dist: black>=23.0.0; extra == "dev"
Requires-Dist: flake8>=6.0.0; extra == "dev"
